Workbook

Sheet Титульный лист
H11: ФЕДЕРАЛЬНОЕ СТАТИСТИЧЕСКОЕ НАБЛЮДЕНИЕ
H13: КОНФИДЕНЦИАЛЬНОСТЬ ГАРАНТИРУЕТСЯ ПОЛУЧАТЕЛЕМ ИНФОРМАЦИИ
E15: Нарушение порядка предоставления первичных статистических данных или несвоевременное предоставление этих данных, либо предоставление недостоверных первичных статистических данных влечет ответственность, установленную Кодексом Российской Федерации об административных правонарушениях
K17: ВОЗМОЖНО ПРЕДОСТАВЛЕНИЕ В ЭЛЕКТРОННОМ ВИДЕ
K19: СВЕДЕНИЯ О ДЕЯТЕЛЬНОСТИ ОРГАНИЗАЦИИ, ОСУЩЕСТВЛЯЮЩЕЙ ОБРАЗОВАТЕЛЬНУЮ ДЕЯТЕЛЬНОСТЬ ПО ОСНОВНЫМ ПРОГРАММАМ ПРОФЕССИОНАЛЬНОГО ОБУЧЕНИЯ
K20: за | AO20: 2024 | AR20: год
A22: Предоставляют: | AV22: Сроки предоставления | BO22: Форма № ПО
A23: юридические лица, осуществляющие образовательную деятельность по основным программам профессионального обучения, индивидуальные предприниматели: | AV23: 20 января после отчетного периода | BL23: Приказ Росстата: Об утверждении формы от 28.12.2023 № 701 О внесении изменений (при наличии) от ___________ № ____ от ___________ № ____
A24: - Министерству просвещения Российской Федерации
BO26: Годовая
A29: Наименование отчитывающейся организации | X29: Общество с ограниченной ответственностью "Институт современных образовательных технологий"
A30: Почтовый адрес | X30: 450058, Республика Башкортостан, г.Уфа, ул. пр-кт Октября, 49А, каб.305
A31: Код формы по ОКУД | V31: Код
V32: отчитывающейся организации (индивидуального предпринимателя) по ОКПО (для обособленного подразделения юридического лица – идентификационный номер)
A37: 1 | V37: 2 | AP37: 3 | BJ37: 4
A38: 609563 | V38: 84137046 | AP38: 278979526 | BJ38: 27801001

Sheet Раздел 1.1
A14: Раздел 1. Сведения об организации
A15: 1.1. Тип, статус и месторасположение организации
A17: Наименование показателей | O17: № строки | P17: Код: да – 1, нет – 0
P18: Тип и статус организации | Q18: Тип поселения
Q19: городские поселения | R19: сельские поселения
A20: 1 | O20: 2 | P20: 3 | Q20: 4 | R20: 5
A21: Профессиональная образовательная организация | O21: 1
A22: Обособленное подразделение (филиал) профессиональной образовательной организации | O22: 2
A23: Общеобразовательная организация | O23: 3
A24: Обособленное подразделение (филиал) общеобразовательной организации | O24: 4
A25: Образовательная организация высшего образования | O25: 5
A26: Обособленное подразделение (филиал) образовательной организации высшего образования | O26: 6
A27: Организация дополнительного образования | O27: 7 | P27: 1 | Q27: 1
A28: Обособленное подразделение (филиал) организации дополнительного образования | O28: 8
A29: Организация дополнительного профессионального образования | O29: 9
A30: Обособленное подразделение (филиал) организации дополнительного профессионального образования | O30: 10
A31: Научная организация | O31: 11
A32: Обособленное подразделение (филиал) научной организации | O32: 12
A33: Иная организация | O33: 13
A34: Обособленное подразделение (филиал) иной организации | O34: 14

Sheet Раздел 1.2
A17: 1.2. Сведения о наличии лицензии на осуществление образовательной деятельности и органов управления
A19: Наименование показателей | O19: № строки | P19: Код: да – 1, нет – 0
A20: 1 | O20: 2 | P20: 3
A21: Лицензия | O21: 1 | P21: 1
A22: Коллегиальные органы управления | O22: 2
A23: в том числе с участием общественности (родителей, работодателей) | O23: 3

Sheet Раздел 1.3
A16: 1.3.Сведения об образовательных программах, реализуемых организацией
A17: Код по ОКЕИ: единица – 642, человек – 792
A18: Наименование образовательных программ | O18: № строки | P18: Число реали-зованных образователь-ных программ-всего, единиц | Q18: из них прошли профессио-нально-общественную аккредитацию работода-телями и их объединениями | R18: Всего обучено, человек | S18: Сетевая форма реализации образовательных программ | W18: Электронное обучение | Z18: Дистанционные образовательные технологии
S19: число программ (из графы 3), реализуемых с использова-нием сетевой формы | T19: численность обученных (из графы 5), осваивающих программы с использова-нием сетевой формы - всего | U19: общее число заключенных договоров с организациями на реализацию образователь-ных программ с использова-нием сетевой формы | V19: число органи-заций, с кото-рыми заклю-чены договоры на реализацию образователь-ных программ с использова-нием сетевой формы | W19: число программ (из графы 3), реализуемых с применением электронного обучения | X19: численность обученных (из графы 5) по программам с применением электронного обучения | Y19: в том числе (из графы 11) с применением исключительно электронного обучения | Z19: число программ (из графы 3), реа-лизованных с применением дистанционных образователь-ных технологий | AA19: численность обученных (из графы 5) по программам с применением дистанционных образователь-ных технологий | AB19: в том числе (из графы 14) с применением исключительно дистанционных образователь-ных технологий
A20: 1 | O20: 2 | P20: 3 | Q20: 4 | R20: 5 | S20: 6 | T20: 7 | U20: 8 | V20: 9 | W20: 10 | X20: 11 | Y20: 12 | Z20: 13 | AA20: 14 | AB20: 15
A21: Программы профессиональной подготовки по профессиям рабочих, служащих | O21: 1
A22: Программы переподготовки рабочих, служащих | O22: 2
A23: Программы повышения квалификации рабочих,служащих | O23: 3

Sheet Раздел 1.4
A17: 1.4. Структура организации
A18: Код по ОКЕИ: единица – 642
A19: Наименование показателей | O19: № строки | P19: Число подразделений
A20: 1 | O20: 2 | P20: 3
A21: Учебно-производственные мастерские | O21: 1
A22: Учебные полигоны | O22: 2
A23: Учебные базы практик | O23: 3
A24: Структурные подразделения, обеспечивающие практическую подготовку слушателей, на базе предприятий / организаций, осуществляющих деятельность по профилю реализуемых образовательных программ | O24: 4
A25: из них на базе предприятий и организаций реального сектора экономики | O25: 5
A26: Справка 1. Число организаций, являющихся базами практики, с которыми оформлены договорные отношения (ед) | O26: 6
A27: В том числе обеспечивают возможность практики всех слушателей программ профессионального обучения в соответствии с учебным планом (ед) | O27: 7

Sheet Раздел 2.1.1
A14: 2.1. Распределение слушателей, обученных по программам профессионального обучения, по профессиям рабочих и должностям служащих
A15: 2.1.1 Программы профессиональной подготовки по профессиям рабочих, должностям служащих
A16: Код по ОКЕИ: человек – 792
A17: Наименование профессии по перечню профессий рабочих, должностей служащих, по которым осуществляется профессиональное обучение, утв. приказом Минобрнауки России от 14 июля 2023 г. № 534 | N17: № строки | O17: Порядковый номер профессии в перечне | P17: Порядковый номер профессии в перечне | Q17: Код профес-сии (при наличии) | R17: Всего обучено (выпуск) (сумма гр. 6–9; 13–15) | S17: В том числе | Z17: Из графы 5
S18: за счет бюджетных ассигнований | V18: по догово-рам об ока-зании плат-ных образо-вательных услуг - всего (сумма гр. 10–12 по итоговым строкам) | W18: в том числе (из гр. 9) – за счет средств: | Z18: обучено по форме обучения | AC18: женщины | AD18: прошли ускоренное обучение по индивидуаль-ным учебным планам | AE18: лица с ограничен-ными возможнос-тями здоровья, инвалиды, дети-инвалиды | AF18: обучающи-еся по образова-тельным программам основного общего образования | AG18: обучающи-еся по образо-вательным программам среднего общего образования
S19: федераль-ного бюджета | T19: бюджета субъекта Российской Федерации | U19: местного бюджета | W19: лиц, зачисляемых на обучение (родителей (законных представи-телей) несо-вершенно-летних обу-чающихся) | X19: иных физических лиц | Y19: юридичес-ких лиц | Z19: очной | AA19: очно-заочной | AB19: заочной
A20: 1 | N20: 2 | O20: 3 | P20: 3 | Q20: 4 | R20: 5 | S20: 6 | T20: 7 | U20: 8 | V20: 9 | W20: 10 | X20: 11 | Y20: 12 | Z20: 13 | AA20: 14 | AB20: 15 | AC20: 16 | AD20: 17 | AE20: 18 | AF20: 19 | AG20: 20
A21: Всего | N21: 1
A22: =IF(ISBLANK(Q22),"",VLOOKUP(Q22,Spravochnik!$B$1:$D$5143,2,FALSE())) -> Монтажник наружных трубопроводов | N22: 2 | O22: =IF(ISBLANK(Q22),"",VLOOKUP(Q22,Spravochnik!$B$1:$D$5143,3,FALSE())) -> 3782 | P22: =O22 -> 3782 | Q22: 14571
A23: =IF(ISBLANK(Q23),"",VLOOKUP(Q23,Spravochnik!$B$1:$D$5143,2,FALSE())) -> Монтажник технологических трубопроводов | N23: 3 | O23: =IF(ISBLANK(Q23),"",VLOOKUP(Q23,Spravochnik!$B$1:$D$5143,3,FALSE())) -> 3797 | P23: =O23 -> 3797 | Q23: 14641
A24: =IF(ISBLANK(Q24),"",VLOOKUP(Q24,Spravochnik!$B$1:$D$5143,2,FALSE())) -> Машинист буровой установки | N24: 4 | O24: =IF(ISBLANK(Q24),"",VLOOKUP(Q24,Spravochnik!$B$1:$D$5143,3,FALSE())) -> 449 | P24: =O24 -> 449 | Q24: 13590
A25: =IF(ISBLANK(Q25),"",VLOOKUP(Q25,Spravochnik!$B$1:$D$5143,2,FALSE())) -> Машинист компрессорных установок | N25: 5 | O25: =IF(ISBLANK(Q25),"",VLOOKUP(Q25,Spravochnik!$B$1:$D$5143,3,FALSE())) -> 3311 | P25: =O25 -> 3311 | Q25: 13775
A26: =IF(ISBLANK(Q26),"",VLOOKUP(Q26,Spravochnik!$B$1:$D$5143,2,FALSE())) -> Оператор газораспределительной станции | N26: 6 | O26: =IF(ISBLANK(Q26),"",VLOOKUP(Q26,Spravochnik!$B$1:$D$5143,3,FALSE())) -> 575 | P26: =O26 -> 575 | Q26: 15553
A27: =IF(ISBLANK(Q27),"",VLOOKUP(Q27,Spravochnik!$B$1:$D$5143,2,FALSE())) -> Плотник | N27: 7 | O27: =IF(ISBLANK(Q27),"",VLOOKUP(Q27,Spravochnik!$B$1:$D$5143,3,FALSE())) -> 3876 | P27: =O27 -> 3876 | Q27: 16671
A28: =IF(ISBLANK(Q28),"",VLOOKUP(Q28,Spravochnik!$B$1:$D$5143,2,FALSE())) -> Слесарь механосборочных работ | N28: 8 | O28: =IF(ISBLANK(Q28),"",VLOOKUP(Q28,Spravochnik!$B$1:$D$5143,3,FALSE())) -> 61 | P28: =O28 -> 61 | Q28: 18466
A29: =IF(ISBLANK(Q29),"",VLOOKUP(Q29,Spravochnik!$B$1:$D$5143,2,FALSE())) -> Оператор технологических установок | N29: 9 | O29: =IF(ISBLANK(Q29),"",VLOOKUP(Q29,Spravochnik!$B$1:$D$5143,3,FALSE())) -> 595 | P29: =O29 -> 595 | Q29: 16081
A30: =IF(ISBLANK(Q30),"",VLOOKUP(Q30,Spravochnik!$B$1:$D$5143,2,FALSE())) -> Слесарь по контрольно-измерительным приборам и автоматике | N30: 10 | O30: =IF(ISBLANK(Q30),"",VLOOKUP(Q30,Spravochnik!$B$1:$D$5143,3,FALSE())) -> 3433 | P30: =O30 -> 3433 | Q30: 18494
A31: =IF(ISBLANK(Q31),"",VLOOKUP(Q31,Spravochnik!$B$1:$D$5143,2,FALSE())) -> Наладчик автоматических линий и агрегатных станков | N31: 11 | O31: =IF(ISBLANK(Q31),"",VLOOKUP(Q31,Spravochnik!$B$1:$D$5143,3,FALSE())) -> 2166 | P31: =O31 -> 2166 | Q31: 14899
A32: =IF(ISBLANK(Q32),"",VLOOKUP(Q32,Spravochnik!$B$1:$D$5143,2,FALSE())) -> Электромонтер по эксплуатации распределительных сетей | N32: 12 | O32: =IF(ISBLANK(Q32),"",VLOOKUP(Q32,Spravochnik!$B$1:$D$5143,3,FALSE())) -> 4932 | P32: =O32 -> 4932 | Q32: 19867
A33: =IF(ISBLANK(Q33),"",VLOOKUP(Q33,Spravochnik!$B$1:$D$5143,2,FALSE())) -> Аппаратчик перегонки | N33: 13 | O33: =IF(ISBLANK(Q33),"",VLOOKUP(Q33,Spravochnik!$B$1:$D$5143,3,FALSE())) -> 4318 | P33: =O33 -> 4318 | Q33: 10501
... A124: =IF(ISBLANK(Q124),"",VLOOKUP(Q124,Spravochnik!$B$1:$D$5143,2,FALSE())) -> Газорезчик | N124: 104 | O124: =IF(ISBLANK(Q124),"",VLOOKUP(Q124,Spravochnik!$B$1:$D$5143,3,FALSE())) -> 3208 | P124: =O124 -> 3208 | Q124: 11618
A125: =IF(ISBLANK(Q125),"",VLOOKUP(Q125,Spravochnik!$B$1:$D$5143,2,FALSE())) | N125: 105 | O125: =IF(ISBLANK(Q125),"",VLOOKUP(Q125,Spravochnik!$B$1:$D$5143,3,FALSE())) | P125: =O125
A126: =IF(ISBLANK(Q126),"",VLOOKUP(Q126,Spravochnik!$B$1:$D$5143,2,FALSE())) | N126: 106 | O126: =IF(ISBLANK(Q126),"",VLOOKUP(Q126,Spravochnik!$B$1:$D$5143,3,FALSE())) | P126: =O126
A127: =IF(ISBLANK(Q127),"",VLOOKUP(Q127,Spravochnik!$B$1:$D$5143,2,FALSE())) | N127: 107 | O127: =IF(ISBLANK(Q127),"",VLOOKUP(Q127,Spravochnik!$B$1:$D$5143,3,FALSE())) | P127: =O127
A128: =IF(ISBLANK(Q128),"",VLOOKUP(Q128,Spravochnik!$B$1:$D$5143,2,FALSE())) | N128: 108 | O128: =IF(ISBLANK(Q128),"",VLOOKUP(Q128,Spravochnik!$B$1:$D$5143,3,FALSE())) | P128: =O128
A129: =IF(ISBLANK(Q129),"",VLOOKUP(Q129,Spravochnik!$B$1:$D$5143,2,FALSE())) | N129: 109 | O129: =IF(ISBLANK(Q129),"",VLOOKUP(Q129,Spravochnik!$B$1:$D$5143,3,FALSE())) | P129: =O129
A130: =IF(ISBLANK(Q130),"",VLOOKUP(Q130,Spravochnik!$B$1:$D$5143,2,FALSE())) | N130: 110 | O130: =IF(ISBLANK(Q130),"",VLOOKUP(Q130,Spravochnik!$B$1:$D$5143,3,FALSE())) | P130: =O130
A131: =IF(ISBLANK(Q131),"",VLOOKUP(Q131,Spravochnik!$B$1:$D$5143,2,FALSE())) | N131: 111 | O131: =IF(ISBLANK(Q131),"",VLOOKUP(Q131,Spravochnik!$B$1:$D$5143,3,FALSE())) | P131: =O131
A132: =IF(ISBLANK(Q132),"",VLOOKUP(Q132,Spravochnik!$B$1:$D$5143,2,FALSE())) | N132: 112 | O132: =IF(ISBLANK(Q132),"",VLOOKUP(Q132,Spravochnik!$B$1:$D$5143,3,FALSE())) | P132: =O132
A133: =IF(ISBLANK(Q133),"",VLOOKUP(Q133,Spravochnik!$B$1:$D$5143,2,FALSE())) | N133: 113 | O133: =IF(ISBLANK(Q133),"",VLOOKUP(Q133,Spravochnik!$B$1:$D$5143,3,FALSE())) | P133: =O133
A134: =IF(ISBLANK(Q134),"",VLOOKUP(Q134,Spravochnik!$B$1:$D$5143,2,FALSE())) | N134: 114 | O134: =IF(ISBLANK(Q134),"",VLOOKUP(Q134,Spravochnik!$B$1:$D$5143,3,FALSE())) | P134: =O134
A135: =IF(ISBLANK(Q135),"",VLOOKUP(Q135,Spravochnik!$B$1:$D$5143,2,FALSE())) | N135: 115 | O135: =IF(ISBLANK(Q135),"",VLOOKUP(Q135,Spravochnik!$B$1:$D$5143,3,FALSE())) | P135: =O135
A136: =IF(ISBLANK(Q136),"",VLOOKUP(Q136,Spravochnik!$B$1:$D$5143,2,FALSE())) | N136: 116 | O136: =IF(ISBLANK(Q136),"",VLOOKUP(Q136,Spravochnik!$B$1:$D$5143,3,FALSE())) | P136: =O136
... A473: =IF(ISBLANK(Q473),"",VLOOKUP(Q473,Spravochnik!$B$1:$D$5143,2,FALSE())) | N473: 453 | O473: =IF(ISBLANK(Q473),"",VLOOKUP(Q473,Spravochnik!$B$1:$D$5143,3,FALSE())) | P473: =O473

Sheet Раздел 2.1.2
A14: 2.1. Распределение слушателей, обученных по программам профессионального обучения, по профессиям рабочих и должностям служащих
A15: 2.1.2 Программы переподготовки рабочих, служащих
A16: Код по ОКЕИ: человек – 792
A17: Наименование профессии по перечню профессий рабочих, должностей служащих, по которым осуществляется профессиональное обучение, утв. приказом Минобрнауки России от 14 июля 2023 г. № 534 | N17: № строки | O17: Порядковый номер профессии в перечне | P17: Порядковый номер профессии в перечне | Q17: Код профес-сии (при наличии) | R17: Всего обучено (выпуск) (сумма гр. 6–9; 13–15) | S17: В том числе | Z17: Из графы 5
S18: за счет бюджетных ассигнований | V18: по догово-рам об ока-зании плат-ных образо-вательных услуг - всего (сумма гр. 10–12 по итоговым строкам) | W18: в том числе (из гр. 9) – за счет средств: | Z18: обучено по форме обучения | AC18: женщины | AD18: прошли ускоренное обучение по индивидуаль-ным учебным планам | AE18: лица с ограничен-ными возможнос-тями здоровья, инвалиды, дети-инвалиды | AF18: обучающи-еся по образова-тельным программам основного общего образования | AG18: обучающи-еся по образо-вательным программам среднего общего образования
S19: федераль-ного бюджета | T19: бюджета субъекта Российской Федерации | U19: местного бюджета | W19: лиц, зачисляемых на обучение (родителей (законных представи-телей) несо-вершенно-летних обу-чающихся) | X19: иных физических лиц | Y19: юридичес-ких лиц | Z19: очной | AA19: очно-заочной | AB19: заочной
A20: 1 | N20: 2 | O20: 3 | P20: 3 | Q20: 4 | R20: 5 | S20: 6 | T20: 7 | U20: 8 | V20: 9 | W20: 10 | X20: 11 | Y20: 12 | Z20: 13 | AA20: 14 | AB20: 15 | AC20: 16 | AD20: 17 | AE20: 18 | AF20: 19 | AG20: 20
A21: Всего | N21: 1
A22: =IF(ISBLANK(Q22),"",VLOOKUP(Q22,Spravochnik!$B$1:$D$5143,2,FALSE())) | N22: 2 | O22: =IF(ISBLANK(Q22),"",VLOOKUP(Q22,Spravochnik!$B$1:$D$5143,3,FALSE())) | P22: =O22
A23: =IF(ISBLANK(Q23),"",VLOOKUP(Q23,Spravochnik!$B$1:$D$5143,2,FALSE())) | N23: 3 | O23: =IF(ISBLANK(Q23),"",VLOOKUP(Q23,Spravochnik!$B$1:$D$5143,3,FALSE())) | P23: =O23
A24: =IF(ISBLANK(Q24),"",VLOOKUP(Q24,Spravochnik!$B$1:$D$5143,2,FALSE())) | N24: 4 | O24: =IF(ISBLANK(Q24),"",VLOOKUP(Q24,Spravochnik!$B$1:$D$5143,3,FALSE())) | P24: =O24
A25: =IF(ISBLANK(Q25),"",VLOOKUP(Q25,Spravochnik!$B$1:$D$5143,2,FALSE())) | N25: 5 | O25: =IF(ISBLANK(Q25),"",VLOOKUP(Q25,Spravochnik!$B$1:$D$5143,3,FALSE())) | P25: =O25
A26: =IF(ISBLANK(Q26),"",VLOOKUP(Q26,Spravochnik!$B$1:$D$5143,2,FALSE())) | N26: 6 | O26: =IF(ISBLANK(Q26),"",VLOOKUP(Q26,Spravochnik!$B$1:$D$5143,3,FALSE())) | P26: =O26
A27: =IF(ISBLANK(Q27),"",VLOOKUP(Q27,Spravochnik!$B$1:$D$5143,2,FALSE())) | N27: 7 | O27: =IF(ISBLANK(Q27),"",VLOOKUP(Q27,Spravochnik!$B$1:$D$5143,3,FALSE())) | P27: =O27
A28: =IF(ISBLANK(Q28),"",VLOOKUP(Q28,Spravochnik!$B$1:$D$5143,2,FALSE())) | N28: 8 | O28: =IF(ISBLANK(Q28),"",VLOOKUP(Q28,Spravochnik!$B$1:$D$5143,3,FALSE())) | P28: =O28
A29: =IF(ISBLANK(Q29),"",VLOOKUP(Q29,Spravochnik!$B$1:$D$5143,2,FALSE())) | N29: 9 | O29: =IF(ISBLANK(Q29),"",VLOOKUP(Q29,Spravochnik!$B$1:$D$5143,3,FALSE())) | P29: =O29
A30: =IF(ISBLANK(Q30),"",VLOOKUP(Q30,Spravochnik!$B$1:$D$5143,2,FALSE())) | N30: 10 | O30: =IF(ISBLANK(Q30),"",VLOOKUP(Q30,Spravochnik!$B$1:$D$5143,3,FALSE())) | P30: =O30
A31: =IF(ISBLANK(Q31),"",VLOOKUP(Q31,Spravochnik!$B$1:$D$5143,2,FALSE())) | N31: 11 | O31: =IF(ISBLANK(Q31),"",VLOOKUP(Q31,Spravochnik!$B$1:$D$5143,3,FALSE())) | P31: =O31
A32: =IF(ISBLANK(Q32),"",VLOOKUP(Q32,Spravochnik!$B$1:$D$5143,2,FALSE())) | N32: 12 | O32: =IF(ISBLANK(Q32),"",VLOOKUP(Q32,Spravochnik!$B$1:$D$5143,3,FALSE())) | P32: =O32
A33: =IF(ISBLANK(Q33),"",VLOOKUP(Q33,Spravochnik!$B$1:$D$5143,2,FALSE())) | N33: 13 | O33: =IF(ISBLANK(Q33),"",VLOOKUP(Q33,Spravochnik!$B$1:$D$5143,3,FALSE())) | P33: =O33
... A473: =IF(ISBLANK(Q473),"",VLOOKUP(Q473,Spravochnik!$B$1:$D$5143,2,FALSE())) | N473: 453 | O473: =IF(ISBLANK(Q473),"",VLOOKUP(Q473,Spravochnik!$B$1:$D$5143,3,FALSE())) | P473: =O473

Sheet Раздел 2.1.3
A14: 2.1. Распределение слушателей, обученных по программам профессионального обучения, по профессиям рабочих и должностям служащих
A15: 2.1.3 Программы повышения квалификации рабочих, служащих
A16: Код по ОКЕИ: человек – 792
A17: Наименование профессии по перечню профессий рабочих, должностей служащих, по которым осуществляется профессиональное обучение, утв. приказом Минобрнауки России от 14 июля 2023 г. № 534 | N17: № строки | O17: Порядковый номер профессии в перечне | P17: Порядковый номер профессии в перечне | Q17: Код профес-сии (при наличии) | R17: Всего обучено (выпуск) (сумма гр. 6–9; 13–15) | S17: В том числе | Z17: Из графы 5
S18: за счет бюджетных ассигнований | V18: по догово-рам об ока-зании плат-ных образо-вательных услуг - всего (сумма гр. 10–12 по итоговым строкам) | W18: в том числе (из гр. 9) – за счет средств: | Z18: обучено по форме обучения | AC18: женщины | AD18: прошли ускоренное обучение по индивидуаль-ным учебным планам | AE18: лица с ограничен-ными возможнос-тями здоровья, инвалиды, дети-инвалиды | AF18: обучающи-еся по образова-тельным программам основного общего образования | AG18: обучающи-еся по образо-вательным программам среднего общего образования
S19: федераль-ного бюджета | T19: бюджета субъекта Российской Федерации | U19: местного бюджета | W19: лиц, зачисляемых на обучение (родителей (законных представи-телей) несо-вершенно-летних обу-чающихся) | X19: иных физических лиц | Y19: юридичес-ких лиц | Z19: очной | AA19: очно-заочной | AB19: заочной
A20: 1 | N20: 2 | O20: 3 | P20: 3 | Q20: 4 | R20: 5 | S20: 6 | T20: 7 | U20: 8 | V20: 9 | W20: 10 | X20: 11 | Y20: 12 | Z20: 13 | AA20: 14 | AB20: 15 | AC20: 16 | AD20: 17 | AE20: 18 | AF20: 19 | AG20: 20
A21: Всего | N21: 1
A22: =IF(ISBLANK(Q22),"",VLOOKUP(Q22,Spravochnik!$B$1:$D$5143,2,FALSE())) | N22: 2 | O22: =IF(ISBLANK(Q22),"",VLOOKUP(Q22,Spravochnik!$B$1:$D$5143,3,FALSE())) | P22: =O22
A23: =IF(ISBLANK(Q23),"",VLOOKUP(Q23,Spravochnik!$B$1:$D$5143,2,FALSE())) | N23: 3 | O23: =IF(ISBLANK(Q23),"",VLOOKUP(Q23,Spravochnik!$B$1:$D$5143,3,FALSE())) | P23: =O23
A24: =IF(ISBLANK(Q24),"",VLOOKUP(Q24,Spravochnik!$B$1:$D$5143,2,FALSE())) | N24: 4 | O24: =IF(ISBLANK(Q24),"",VLOOKUP(Q24,Spravochnik!$B$1:$D$5143,3,FALSE())) | P24: =O24
A25: =IF(ISBLANK(Q25),"",VLOOKUP(Q25,Spravochnik!$B$1:$D$5143,2,FALSE())) | N25: 5 | O25: =IF(ISBLANK(Q25),"",VLOOKUP(Q25,Spravochnik!$B$1:$D$5143,3,FALSE())) | P25: =O25
A26: =IF(ISBLANK(Q26),"",VLOOKUP(Q26,Spravochnik!$B$1:$D$5143,2,FALSE())) | N26: 6 | O26: =IF(ISBLANK(Q26),"",VLOOKUP(Q26,Spravochnik!$B$1:$D$5143,3,FALSE())) | P26: =O26
A27: =IF(ISBLANK(Q27),"",VLOOKUP(Q27,Spravochnik!$B$1:$D$5143,2,FALSE())) | N27: 7 | O27: =IF(ISBLANK(Q27),"",VLOOKUP(Q27,Spravochnik!$B$1:$D$5143,3,FALSE())) | P27: =O27
A28: =IF(ISBLANK(Q28),"",VLOOKUP(Q28,Spravochnik!$B$1:$D$5143,2,FALSE())) | N28: 8 | O28: =IF(ISBLANK(Q28),"",VLOOKUP(Q28,Spravochnik!$B$1:$D$5143,3,FALSE())) | P28: =O28
A29: =IF(ISBLANK(Q29),"",VLOOKUP(Q29,Spravochnik!$B$1:$D$5143,2,FALSE())) | N29: 9 | O29: =IF(ISBLANK(Q29),"",VLOOKUP(Q29,Spravochnik!$B$1:$D$5143,3,FALSE())) | P29: =O29
A30: =IF(ISBLANK(Q30),"",VLOOKUP(Q30,Spravochnik!$B$1:$D$5143,2,FALSE())) | N30: 10 | O30: =IF(ISBLANK(Q30),"",VLOOKUP(Q30,Spravochnik!$B$1:$D$5143,3,FALSE())) | P30: =O30
A31: =IF(ISBLANK(Q31),"",VLOOKUP(Q31,Spravochnik!$B$1:$D$5143,2,FALSE())) | N31: 11 | O31: =IF(ISBLANK(Q31),"",VLOOKUP(Q31,Spravochnik!$B$1:$D$5143,3,FALSE())) | P31: =O31
A32: =IF(ISBLANK(Q32),"",VLOOKUP(Q32,Spravochnik!$B$1:$D$5143,2,FALSE())) | N32: 12 | O32: =IF(ISBLANK(Q32),"",VLOOKUP(Q32,Spravochnik!$B$1:$D$5143,3,FALSE())) | P32: =O32
A33: =IF(ISBLANK(Q33),"",VLOOKUP(Q33,Spravochnik!$B$1:$D$5143,2,FALSE())) | N33: 13 | O33: =IF(ISBLANK(Q33),"",VLOOKUP(Q33,Spravochnik!$B$1:$D$5143,3,FALSE())) | P33: =O33
... A473: =IF(ISBLANK(Q473),"",VLOOKUP(Q473,Spravochnik!$B$1:$D$5143,2,FALSE())) | N473: 453 | O473: =IF(ISBLANK(Q473),"",VLOOKUP(Q473,Spravochnik!$B$1:$D$5143,3,FALSE())) | P473: =O473

Sheet Раздел 2.2
A16: 2.2. Обучение отдельных категорий слушателей
A17: Код по ОКЕИ: человек – 792
A18: Наименование показателя | O18: № строки | P18: Программы профессионального обучения – всего (сумма гр. 4–6) | Q18: В том числе
Q19: программы профессиональной подготовки по профессиям рабочих, должностям служащих | R19: программы переподготовки рабочих, служащих | S19: программы повышения квалификации рабочих, служащих
A20: 1 | O20: 2 | P20: 3 | Q20: 4 | R20: 5 | S20: 6
A21: Обучено слушателей: по направлению органов службы занятости (сумма строк 02–04) | O21: 1
A22: из них: безработные | O22: 2
A23: женщины в период отпуска по уходу за ребенком по достижении им возраста трех лет | O23: 3
A24: незанятые граждане, которым назначена трудовая пенсия по старости и которые стремятся возобновить трудовую деятельность | O24: 4
A25: работников организаций за счет средств работодателя | O25: 5
A26: по запросам организаций (кроме лиц, указанных в строке 05) | O26: 6
A27: лиц, получивших повреждение здоровья вследствие несчастных случаев на производстве и профессиональных заболеваний по страховому случаю за счет средств страховщика | O27: 7
A28: осужденных к лишению свободы | O28: 8 | R28: X | S28: X

Sheet Раздел 2.3
A15: 2.3. Обучение лиц с ограниченными возможностями здоровья и инвалидов
A16: Код по ОКЕИ: человек – 792
A17: Наименование показателей | O17: № строки | P17: Программы профессионального обучения | T17: Из них адаптированные программы профессионального обучения
P18: Всего (сумма гр. 4–6) | Q18: в том числе | T18: Всего (сумма гр. 8–10) | U18: в том числе
Q19: программы профессиональ-ной подготовки по профессиям рабочих, должностям служащих | R19: программы переподготовки рабочих, служащих | S19: программы повышения квалификации рабочих, служащих | U19: программы профессиональ-ной подготовки по профессиям рабочих, должностям служащих (из графы 4) | V19: программы переподготовки рабочих, служащих (из графы 5) | W19: программы повышения квалификации рабочих, служащих (из графы 6)
A20: 1 | O20: 2 | P20: 3 | Q20: 4 | R20: 5 | S20: 6 | T20: 7 | U20: 8 | V20: 9 | W20: 10
A21: Все группы | B21: Обучено слушателей с ограниченными возможностями здоровья | O21: 1
B22: из них: инвалиды | O22: 2
B23: дети-инвалиды | O23: 3
B24: инвалиды (кроме учтенных в стр. 02) | O24: 4
B25: дети-инвалиды (кроме учтенных в стр. 03) | O25: 5
A26: Из них отдельные группы для лиц с огра-ниченными возмож-ностями здоровья | B26: Обучено слушателей с ограниченными возможностями здоровья (из строки 01) | O26: 6
B27: из них: инвалиды | O27: 7
B28: дети-инвалиды | O28: 8
B29: инвалиды (из строки 04) | O29: 9
B30: дети-инвалиды (из строки 05) | O30: 10

Sheet Раздел 2.4
A17: 2.4. Распределение слушателей, обученных по программам профессионального обучения, по уровню образования
A18: Код по ОКЕИ: человек – 792
A19: Наименование показателей | O19: № строки | P19: Программы профессио-нальной подготовки по профессиям рабочих, должностям служащих | Q19: Программы переподготовки рабочих, служащих | R19: Программы повышения квалификации рабочих, служащих
A20: 1 | O20: 2 | P20: 3 | Q20: 4 | R20: 5
A21: Всего обучено (сумма строк 02, 04, 06, 08, 10, 11, 13, 15, 17) | O21: 1
A22: в том числе имеют образование: основное общее | O22: 2
A23: из них получили указанное образование в отчетном году | O23: 3
A24: среднее общее | O24: 4
A25: из них получили указанное образование в отчетном году | O25: 5
A26: среднее профессиональное по программам подготовки квалифицированных рабочих, служащих | O26: 6
A27: из них получили указанное образование в отчетном году | O27: 7
A28: среднее профессиональное по программам подготовки специалистов среднего звена | O28: 8
A29: из них получили указанное образование в отчетном году | O29: 9
A30: имеют диплом о неполном высшем образовании (выдавался до 1 января 2014 г.) | O30: 10
A31: высшее, подтвержденное дипломом: бакалавра | O31: 11
A32: из них получили указанное образование в отчетном году | O32: 12
... A40: из них лица с различными формами умственной отсталости (интеллектуальными нарушениями) | O40: 20

Sheet Раздел 2.5
A15: 2.5. Распределение слушателей, обученных по программам профессионального обучения, по гражданству
A16: Код по ОКЕИ: человек – 792
A17: Наименование показателей | O17: № строки | P17: Код госу-дарства по ОКСМ | Q17: Программы профессиональной подготовки по профессиям рабочих, должностям служащих | U17: Программы переподготовки рабочих, служащих | Y17: Программы повышения квалификации рабочих, служащих
Q18: обучено за счет бюджетных ассигнований | T18: по договорам об оказании платных образова-тельных услуг | U18: обучено за счет бюджетных ассигнований | X18: по договорам об оказании платных образова-тельных услуг | Y18: обучено за счет бюджетных ассигнований | AB18: по договорам об оказании платных об-разователь-ных услуг
Q19: федераль-ного бюджета | R19: бюджета субъекта Российской Федерации | S19: местного бюджета | U19: федераль-ного бюджета | V19: бюджета субъекта Российской Федерации | W19: местного бюджета | Y19: федерального бюджета | Z19: бюджета субъекта Российской Федерации | AA19: местного бюджета
A20: 1 | O20: 2 | P20: 3 | Q20: 4 | R20: 5 | S20: 6 | T20: 7 | U20: 8 | V20: 9 | W20: 10 | X20: 11 | Y20: 12 | Z20: 13 | AA20: 14 | AB20: 15
A21: Всего обучено (сумма стр. 02, 03, 21) | O21: 1
A22: в том числе: граждане Российской Федерации | O22: 2 | P22: 643
A23: граждане иностранных государств – всего | O23: 3
A24: из них граждане: Абхазии | O24: 4 | P24: 895
A25: Азербайджана | O25: 5 | P25: 31
A26: Армении | O26: 6 | P26: 51
A27: Беларуси | O27: 7 | P27: 112
A28: Грузии | O28: 8 | P28: 268
A29: Казахстана | O29: 9 | P29: 398
A30: Киргизии | O30: 10 | P30: 417
A31: Латвии | O31: 11 | P31: 428
A32: Литвы | O32: 12 | P32: 440
A33: Республики Молдова | O33: 13 | P33: 498
A34: Таджикистана | O34: 14 | P34: 762
A35: Туркмении | O35: 15 | P35: 795
... A39: Южной Осетии | O39: 19 | P39: 896
A40: других иностранных государств | O40: 20
A41: лица без гражданства | O41: 21

Sheet Раздел 2.6
A16: 2.6. Распределение слушателей, обученных по программам профессионального обучения, по возрасту и полу
A17: Код по ОКЕИ: человек – 792
A18: Наименование показателей | O18: № строки | P18: Программы профессиональной подготовки по профессиям рабочих, должностям служащих | R18: Программы переподготовки рабочих, служащих | T18: Программы повышения квалификации рабочих, служащих
P19: всего обучено | Q19: из них женщины | R19: всего обучено | S19: из них женщины | T19: всего обучено | U19: из них женщины
A20: 1 | O20: 2 | P20: 3 | Q20: 4 | R20: 5 | S20: 6 | T20: 7 | U20: 8
A21: Всего обучено (сумма строк 02–26) | O21: 1
A22: В том числе в возрасте (число полных лет на 1 января календарного года, следующего за отчетным): 14 лет | O22: 2
A23: 15 лет | O23: 3
A24: 16 лет | O24: 4
A25: 17 лет | O25: 5
A26: 18 лет | O26: 6
A27: 19 лет | O27: 7
A28: 20 лет | O28: 8
A29: 21 год | O29: 9
A30: 22 года | O30: 10
A31: 23 года | O31: 11
A32: 24 года | O32: 12
... A46: в возрасте моложе 14 лет | O46: 26

Sheet Раздел 3.1
A13: Раздел 3. Сведения о персонале организации
A14: 3.1. Распределение численности персонала по уровню образования и полу (без внешних совместителей и работающих по договорам гражданско-правового характера)
A15: Код по ОКЕИ: человек – 792 (в целых); единица –642 (с одним десятичным знаком)
A16: Наименование показателей | O16: № строки | P16: Всего, человек | Q16: Из них (из гр.3) имеют образование: | AA16: Из гр.3 | AD16: численность работников в пересчете на полную занятость, единиц
Q17: Высшее | R17: Из них (гр. 4) педаго-гическое | S17: Из гр.4 имеют | X17: среднее про-фессиональ-ное образова-ние по прог-раммам подготовки специалистов среднего звена | Y17: из них (гр. 11) педаго-гическое | Z17: среднее про-фессиональ-ное образова-ние по прог-раммам подготовки квалифи-цированных рабочих, служащих | AA17: имеют квалификационные категории | AC17: женщины
S18: ученую степень | V18: ученое звание | AA18: высшую | AB18: первую
S19: доктора наук | T19: кандидата наук | U19: PhD | V19: профессора | W19: доцента
A20: 1 | O20: 2 | P20: 3 | Q20: 4 | R20: 5 | S20: 6 | T20: 7 | U20: 8 | V20: 9 | W20: 10 | X20: 11 | Y20: 12 | Z20: 13 | AA20: 14 | AB20: 15 | AC20: 16 | AD20: 17
A21: Численность работников – всего (сумма строк 02, 05, 17,18) | O21: 1
A22: в том числе: руководящие работники – всего | O22: 2
A23: из них: руководитель | O23: 3
A24: заместители руководителя | O24: 4
A25: педагогические работники – всего (сумма строк 06,08,10-16) | O25: 5
A26: в том числе: преподаватели | O26: 6
A27: из них осуществляющие образовательную деятельность по реализации образовательных программ профессионального обучения | O27: 7
A28: мастера производственного обучения | O28: 8
A29: из них осуществляющие образовательную деятельность по реализации образовательных программ профессионального обучения | O29: 9
A30: социальные педагоги | O30: 10
A31: педагоги-психологи | O31: 11
A32: педагоги-организаторы | O32: 12
... A46: из них реализующих образовательные программы профессионального обучения (чел) | O46: 26

Sheet Раздел 3.2
A15: 3.2. Распределение персонала по стажу работы
A16: (без внешних совместителей и работающих по договорам гражданско-правового характера)
A17: Код по ОКЕИ: человек – 792
A18: Наименование показателей | O18: № строки | P18: Всего (сумма граф 4-9) | Q18: Из гр. 3 – имеют общий стаж работы, лет | W18: Из гр. 3 имеют стаж педаго-гической работы - всего (сумма граф 11-16) | X18: Из гр. 10 – имеют педагогический стаж работы, лет | AD18: Не имеют педагогичес-кого стажа работы
Q19: до 3 | R19: от 3 до 5 | S19: от 5 до 10 | T19: от 10 до 15 | U19: от 15 до 20 | V19: 20 и более | X19: до 3 | Y19: от 3 до 5 | Z19: от 5 до 10 | AA19: от 10 до 15 | AB19: от 15 до 20 | AC19: 20 и более
A20: 1 | O20: 2 | P20: 3 | Q20: 4 | R20: 5 | S20: 6 | T20: 7 | U20: 8 | V20: 9 | W20: 10 | X20: 11 | Y20: 12 | Z20: 13 | AA20: 14 | AB20: 15 | AC20: 16 | AD20: 17
A21: Численность работников – всего (сумма строк 02, 05, 17,18) | O21: 1
A22: в том числе: руководящие работники – всего | O22: 2
A23: из них: руководитель | O23: 3
A24: заместители руководителя | O24: 4
A25: педагогические работники – всего (сумма строк 06,08,10-16) | O25: 5
A26: в том числе: преподаватели | O26: 6
A27: из них осуществляющие образовательную деятельность по реализации образовательных программ профессионального обучения | O27: 7
A28: мастера производственного обучения | O28: 8
A29: из них осуществляющие образовательную деятельность по реализации образовательных программ профессионального обучения | O29: 9
A30: социальные педагоги | O30: 10
A31: педагоги-психологи | O31: 11
A32: педагоги-организаторы | O32: 12
... A38: иной персонал | O38: 18

Sheet Раздел 3.3.1
A13: 3.3. Численность внешних совместителей и работающих по договорам гражданско - правового характера
A14: 3.3.1. Численность внешних совместителей
A15: Код по ОКЕИ: человек – 792 (в целых); единица –642 (с одним десятичным знаком)
A16: Наименование показателей | O16: № строки | P16: Всего, человек | Q16: Из них (из гр.3) имеют образование: | AA16: Из гр.3 женщины | AB16: численность работников в пересчете на полную занятость, единиц
Q17: Высшее | R17: Из них (гр. 4) педаго-гическое | S17: Из гр.4 имеют | X17: среднее про-фессиональ-ное образова-ние по прог-раммам подготовки специалистов среднего звена | Y17: из них (гр. 11) педаго-гическое | Z17: среднее про-фессиональ-ное образова-ние по прог-раммам подготовки квалифи-цированных рабочих, служащих
S18: ученую степень | V18: ученое звание
S19: доктора наук | T19: кандидата наук | U19: PhD | V19: профессора | W19: доцента
A20: 1 | O20: 2 | P20: 3 | Q20: 4 | R20: 5 | S20: 6 | T20: 7 | U20: 8 | V20: 9 | W20: 10 | X20: 11 | Y20: 12 | Z20: 13 | AA20: 14 | AB20: 15
A21: Численность работников – всего (сумма строк 02, 03, 15, 16) | O21: 1
A22: в том числе: руководящие работники – всего | O22: 2
A23: педагогические работники – всего (сумма строк 04, 06, 08-14) | O23: 3
A24: в том числе: преподаватели | O24: 4
A25: из них осуществляющие образовательную деятельность по реализации образовательных программ профессионального обучения | O25: 5
A26: мастера производственного обучения | O26: 6
A27: из них осуществляющие образовательную деятельность по реализации образовательных программ профессионального обучения | O27: 7
A28: социальные педагоги | O28: 8
A29: педагоги-психологи | O29: 9
A30: педагоги-организаторы | O30: 10
A31: преподаватели-организаторы основ безопасности жизнедеятельности | O31: 11
A32: руководители физического воспитания | O32: 12
... A46: из них реализующих образовательные программы профессионального обучения (чел) | O46: 26

Sheet Раздел 3.3.2
A16: 3.3.2. Численность работников, выполняющих работы по договорам гражданско - правового характера
A17: Код по ОКЕИ: человек – 792
A18: Наименование показателей | O18: № строки | P18: Всего | Q18: Из гр. 3 численность работников предприятий и организаций:
Q19: всего | R19: в том числе предприятий и организаций реального сектора экономики
A20: 1 | O20: 2 | P20: 3 | Q20: 4 | R20: 5
A21: Численность работников, выполняющих работы по договорам гражданско-правового характера – всего | O21: 1
A22: из них осуществляющие образовательную деятельность по реализации образовательных программ профессионального обучения | O22: 2

Sheet Раздел 3.3.3
A17: 3.3.3. Численность работников, осуществляющих образовательную деятельность по реализации образовательных программ профессионального обучения на условиях внутреннего совместительства и совмещения профессий (должностей)
A18: Код по ОКЕИ: человек – 792
A19: Наименование показателей | O19: № строки | P19: Всего
A20: 1 | O20: 2 | P20: 3
A21: Численность работников, осуществляющих образовательную деятельность по реализации образовательных программ профессионального обучения на условиях внутреннего совместительства | O21: 1
A22: Численность работников, осуществляющих образовательную деятельность по реализации образовательных программ профессионального обучения на условиях совмещения профессий (должностей) | O22: 2

Sheet Раздел 3.4
A14: 3.4. Сведения о дополнительном профессиональном образовании персонала
A15: (без внешних совместителей и работающих по договорам гражданско-правового характера)
A16: Код по ОКЕИ: человек – 792
A17: Наименование показателей | O17: № строки | P17: Всего | Q17: Из графы 3 прошли за последние три года: | W17: Из граф 4 – 9 прошли в отчетном году:
Q18: повышение квалификации и (или) профес-сиональную переподготовку | R18: из них: | U18: из них (графы 7) в организациях и предприя- тиях реального сектора экономик | V18: в том числе (из гр.8) в профильных организациях и предприятиях | W18: повышение квалификации и (или) профес-сиональную переподготов-ку (из гр. 4) | X18: из них: | AA18: из них (графы 13) в организа-циях и предприятиях реального сектора экономики | AB18: в том числе (из гр.14) в профильных организациях и предприятиях
R19: по профилю педагогической деятельности | S19: по использова-нию информа-ционных и коммуникаци-онных технологий | T19: в форме стажировки | X19: по профилю педагогической деятельности (из гр. 5) | Y19: по использова-нию информа-ционных и коммуника-ционных технологий (из гр. 6) | Z19: в форме стажировки (из гр. 7)
A20: 1 | O20: 2 | P20: 3 | Q20: 4 | R20: 5 | S20: 6 | T20: 7 | U20: 8 | V20: 9 | W20: 10 | X20: 11 | Y20: 12 | Z20: 13 | AA20: 14 | AB20: 15
A21: Руководящие работники – всего | O21: 1
A22: из них: руководитель | O22: 2
A23: заместители руководителя | O23: 3
A24: Педагогические работники – всего | O24: 4
A25: в том числе: преподаватели | O25: 5
A26: из них осуществляющие образовательную деятельность по реализации образовательных программ профессионального обучения | O26: 6
A27: мастера производственного обучения | O27: 7
A28: из них осуществляющие образовательную деятельность по реализации образовательных программ профессионального обучения | O28: 8
A29: Учебно-вспомогательный персонал | O29: 9

Sheet Раздел 3.5
A16: 3.5. Сведения об иностранных работниках
A17: Код по ОКЕИ: человек – 792 (в целых); единица – 642 (с одним десятичным знаком)
A18: Наименование показателей | O18: № строки | P18: Численность иностранных работников без внешних совместителей и работающих по договорам гражданско-правового характера, человек | Q18: из них граждане: | S18: Численность иностранных работников, работающих на условиях внешнего совмести-тельства, человек | T18: из них граждане: | V18: Численность иностранных работников в пересчете на полную занятость, единиц
Q19: государств-участников СНГ | R19: стран Европейского Союза и США | T19: государств-участников СНГ | U19: стран Европейского Союза и США | V19: без внешних совместителей и работающих по договорам гражданско-правового характера | W19: внешние совместители
A20: 1 | O20: 2 | P20: 3 | Q20: 4 | R20: 5 | S20: 6 | T20: 7 | U20: 8 | V20: 9 | W20: 10
A21: Педагогические работники – всего | O21: 1
A22: в том числе: преподаватели | O22: 2
A23: из них осуществляющие образовательную деятельность по реализации образовательных программ профессионального обучения | O23: 3
A24: мастера производственного обучения | O24: 4
A25: из них осуществляющие образовательную деятельность по реализации образовательных программ профессионального обучения | O25: 5
A26: Учебно-вспомогательный персонал | O26: 6
A27: Справка 4. Численность иностранных специалистов, осуществляющих образовательную деятельность по реализации образовательных программ профессионального обучения по договорам гражданско-правового характера – всего (чел) | O27: 7
A28: из них граждане: государств-участников СНГ (чел) | O28: 8
A29: стран Европейского союза и США (чел) | O29: 9

Sheet Раздел 3.6
A15: 3.6. Движение работников
A16: Код по ОКЕИ: единица – 642 (допускается с двумя десятичными знаками); человек – 792 (в целых)
A17: Наименование показателей | O17: № строки | P17: Число ставок по штату, единиц | Q17: Фактически занято, единиц | S17: Численность работников на начало отчетного года (без внешних совместителей и работавших по договорам гражданско-правового характера), человек | T17: Принято работников, человек | W17: Выбыло работников, человек | Y17: Численность работников на конец отчетно-го года (без совместителей и работающих по договорам гражданско-правового характера), человек
Q18: всего | R18: работниками списочного состава | T18: всего | U18: из них выпускники | W18: всего | X18: из них по собственному желанию
U19: со средним професси-ональным образованием по программам подготовки специалистов среднего звена | V19: с высшим образованием
A20: 1 | O20: 2 | P20: 3 | Q20: 4 | R20: 5 | S20: 6 | T20: 7 | U20: 8 | V20: 9 | W20: 10 | X20: 11 | Y20: 12
A21: Численность работников – всего (сумма строк 02, 05, 17,18) | O21: 1
A22: в том числе: руководящие работники – всего | O22: 2
A23: из них: руководитель | O23: 3
A24: заместители руководителя | O24: 4
A25: педагогические работники – всего (сумма строк 06,08,10-16) | O25: 5
A26: в том числе: преподаватели | O26: 6
A27: из них осуществляющие образовательную деятельность по реализации образовательных программ профессионального обучения | O27: 7
A28: мастера производственного обучения | O28: 8
A29: из них осуществляющие образовательную деятельность по реализации образовательных программ профессионального обучения | O29: 9
A30: социальные педагоги | O30: 10
A31: педагоги-психологи | O31: 11
A32: педагоги-организаторы | O32: 12
... A38: иной персонал | O38: 18

Sheet Раздел 3.7.1
P14: 3.7. Распределение персонала по возрасту и полу
P15: 3.7.1 Распределение персонала без внешних совместителей и работающих по договорам гражданско-правового характера по возрасту и полу
P16: Код по ОКЕИ: человек – 792
A17: Наименование показателей | O17: № строки | P17: Всего (сумма гр.4, 6,8,10,12,14, 16,18,20,22) | Q17: Число полных лет по состоянию на конец отчётного года
Q18: моложе 25 лет | S18: 25–29 | U18: 30–34 | W18: 35–39 | Y18: 40–44 | AA18: 45–49 | AC18: 50–54 | AE18: 55–59 | AG18: 60–64 | AI18: 65 и более
Q19: всего | R19: из них женщины | S19: всего | T19: из них женщины | U19: всего | V19: из них женщины | W19: всего | X19: из них женщины | Y19: всего | Z19: из них женщины | AA19: всего | AB19: из них женщины | AC19: всего | AD19: из них женщины | AE19: всего | AF19: из них женщины | AG19: всего | AH19: из них женщины | AI19: всего | AJ19: из них женщины
A20: 1 | O20: 2 | P20: 3 | Q20: 4 | R20: 5 | S20: 6 | T20: 7 | U20: 8 | V20: 9 | W20: 10 | X20: 11 | Y20: 12 | Z20: 13 | AA20: 14 | AB20: 15 | AC20: 16 | AD20: 17 | AE20: 18 | AF20: 19 | AG20: 20 | AH20: 21 | AI20: 22 | AJ20: 23
A21: Численность работников – всего (сумма строк 02, 05, 17,18) | O21: 1
A22: в том числе: руководящие работники – всего | O22: 2
A23: из них: руководитель | O23: 3
A24: заместители руководителя | O24: 4
A25: педагогические работники – всего (сумма строк 06,08,10-16) | O25: 5
A26: в том числе: преподаватели | O26: 6
A27: из них осуществляющие образовательную деятельность по реализации образовательных программ профессионального обучения | O27: 7
A28: мастера производственного обучения | O28: 8
A29: из них осуществляющие образовательную деятельность по реализации образовательных программ профессионального обучения | O29: 9
A30: социальные педагоги | O30: 10
A31: педагоги-психологи | O31: 11
A32: педагоги-организаторы | O32: 12
... A38: иной персонал | O38: 18

Sheet Раздел 3.7.2
P15: 3.7.2. Распределение педагогических работников и учебно-вспомогательного персонала, работающих на условиях внешнего совместительства, по возрасту и полу
P16: Код по ОКЕИ: человек – 792
A17: Наименование показателей | O17: № строки | P17: Всего (сум-ма гр.4,6, 8,10,12,14,16,18,20,22) | Q17: Число полных лет по состоянию на конец отчётного года
Q18: моложе 25 лет | S18: 25–29 | U18: 30–34 | W18: 35–39 | Y18: 40–44 | AA18: 45–49 | AC18: 50–54 | AE18: 55–59 | AG18: 60–64 | AI18: 65 и более
Q19: всего | R19: из них женщины | S19: всего | T19: из них женщины | U19: всего | V19: из них женщины | W19: всего | X19: из них женщины | Y19: всего | Z19: из них женщины | AA19: всего | AB19: из них женщины | AC19: всего | AD19: из них женщины | AE19: всего | AF19: из них женщины | AG19: всего | AH19: из них женщины | AI19: всего | AJ19: из них женщины
A20: 1 | O20: 2 | P20: 3 | Q20: 4 | R20: 5 | S20: 6 | T20: 7 | U20: 8 | V20: 9 | W20: 10 | X20: 11 | Y20: 12 | Z20: 13 | AA20: 14 | AB20: 15 | AC20: 16 | AD20: 17 | AE20: 18 | AF20: 19 | AG20: 20 | AH20: 21 | AI20: 22 | AJ20: 23
A21: Педагогические работники – всего | O21: 1
A22: в том числе: преподаватели | O22: 2
A23: из них осуществляющие образовательную деятельность по реализации образовательных программ профессионального обучения | O23: 3
A24: мастера производственного обучения | O24: 4
A25: из них осуществляющие образовательную деятельность по реализации образовательных программ профессионального обучения | O25: 5
A26: Учебно-вспомогательный персонал | O26: 6

Sheet Раздел 4.1
A15: Раздел 4. Имущество организации
A16: 4.1. Наличие основных фондов
A17: (на конец отчетного года)
A18: Код по ОКЕИ: тысяча рублей – 384 (с одним десятичным знаком)
A19: Наименование показателей | O19: № строки | P19: Наличие по полной учетной стоимости | Q19: В том числе не старше 5 лет
A20: 1 | O20: 2 | P20: 3 | Q20: 4
A21: Основные фонды – всего (сумма строк 02, 03, 07, 08, 09) | O21: 1
A22: в том числе: здания и сооружения | O22: 2
A23: машины, оборудование | O23: 3
A24: из них: измерительные и регулирующие приборы и устройства, лабораторное оборудование | O24: 4
A25: информационные машины и оборудование (кроме учтенных по стр. 04) | O25: 5
A26: в том числе вычислительная техника | O26: 6
A27: библиотечный фонд | O27: 7
A28: нематериальные основные фонды | O28: 8
A29: прочие виды основных фондов | O29: 9
A30: Из строки 03 – машины и оборудование дорогостоящие (стоимостью свыше 1 млн руб за единицу) | O30: 10

Sheet Раздел 4.2
A15: 4.2. Характеристика здания (зданий)
A16: (на конец отчетного года)
P17: Укажите в графах 3-6, 9-19 по каждой из заполненных строк соответствующий код: да – 1; нет – 0 | X17: Код по ОКЕИ: единица – 642; год – 366
A18: Наименование показателей | O18: № строки | P18: Здание: | T18: Год первоначаль-ного ввода в эксплуатацию | U18: Год последнего капитального ремонта (3) | V18: Характеристика материала стен здания | AD18: Наличие доступа к Wi-Fi
P19: оборудовано системой виде-онаблюдения | Q19: имеет охрану | R19: специально спроектировано и построено под конкретную организацию | S19: доступно для маломобильных групп населения | V19: каменные | W19: кирпичные | X19: панельные | Y19: блочные | Z19: деревянные | AA19: монолитные | AB19: смешанные | AC19: из прочих стеновых материалов | AD19: есть доступ Wi-Fi | AE19: Wi-Fi охватывает более половины площади здания | AF19: доступен для обучающихся
A20: 1 | O20: 2 | P20: 3 | Q20: 4 | R20: 5 | S20: 6 | T20: 7 | U20: 8 | V20: 9 | W20: 10 | X20: 11 | Y20: 12 | Z20: 13 | AA20: 14 | AB20: 15 | AC20: 16 | AD20: 17 | AE20: 18 | AF20: 19
A21: Учебно-лабораторные здания (корпуса): Здание 1 | O21: 1
A22: Здание 2 | O22: 2
A23: Здание 3 | O23: 3
A24: Здание 4 | O24: 4
A25: Здание 5 | O25: 5
A26: Здание 6 | O26: 6
A27: Здание 7 | O27: 7
A28: Здание 8 | O28: 8
A29: Здание 9 | O29: 9
A30: Здание 10 | O30: 10
A31: Здание 11 | O31: 11
A32: Здание 12 | O32: 12
... A75: число мест/коек (ед) | O75: 55
A77: 3 - Укажите в графе 8 знак 0, если в здании не проводился капитальный ремонт.
A78: 4 - Без учета общежитий гостиничного типа.

Sheet Раздел 4.3
A14: 4.3. Наличие и использование площадей
A15: (на конец отчетного года)
A16: Код по ОКЕИ: место – 698; штука – 796; квадратный метр – 055 (в целых); га – 059 (с двумя десятичными знаками)
A17: Наименование показателей | O17: № строки | P17: Всего (сумма граф 9, 10, 11 и 12) | Q17: Из нее площадь:
Q18: сданная в аренду или субаренду | R18: находящаяся на капитальном ремонте | S18: требующая капитального ремонта | T18: находящаяся в аварийном состоянии | U18: оборудован-ная охранно-пожарной сигнализацией | V18: Из гр. 3 площадь по форме владения, пользования
V19: на правах собственности | W19: в оперативном управлении | X19: арендованная | Y19: другие формы владения
A20: 1 | O20: 2 | P20: 3 | Q20: 4 | R20: 5 | S20: 6 | T20: 7 | U20: 8 | V20: 9 | W20: 10 | X20: 11 | Y20: 12
A21: Общая площадь зданий (помещений) – всего (сумма строк 02, 08,10), кв м | O21: 1
A22: из нее площадь по целям использования: учебно-лабораторных зданий (сумма строк 03, 05, 06) | O22: 2
A23: в том числе: учебная | O23: 3
A24: из нее площадь крытых спортивных сооружений | O24: 4
A25: учебно-вспомогательная | O25: 5
A26: подсобная | O26: 6
A27: из нее площадь пунктов общественного питания | O27: 7
A28: общежитий | O28: 8
A29: в том числе жилая | O29: 9
A30: прочих зданий (помещений) | O30: 10
A31: Общая площадь земельных участков – всего, га | O31: 11
A32: из нее площадь по целям использования: учебных полигонов (5) | O32: 12
... A37: Количество автоматизированных тренажерно-обучающих комплексов (систем) (штука) | O37: 17
A39: 5 - Укажите по строке 12 знак 0, если на земельном участке технологическими требованиями не предусмотрены площади учебных полигонов.
A40: 6 - Укажите по строке 13 знак 0, если на земельном участке технологическими требованиями не предусмотрены площади опытных полей.

Sheet Раздел 5
A15: Раздел 5. Количество персональных компьютеров и информационного оборудования
A16: (на конец отчетного года)
A17: Код по ОКЕИ: штука – 796
A18: Наименование показателей | O18: № строки | P18: Всего | Q18: в том числе используемых в учебных целях
Q19: всего | R19: из них доступных для использования слушателями в свободное от основных занятий время
A20: 1 | O20: 2 | P20: 3 | Q20: 4 | R20: 5
A21: Персональные компьютеры – всего | O21: 1
A22: из них: ноутбуки и другие портативные персональные компьютеры (кроме планшетных) | O22: 2
A23: планшетные компьютеры | O23: 3
A24: находящиеся в составе локальных вычислительных сетей | O24: 4
A25: имеющие доступ к Интернету | O25: 5
A26: имеющие доступ к Интранет-порталу организации | O26: 6
A27: поступившие в отчетном году | O27: 7
A28: Электронные терминалы (инфоматы) | O28: 8
A29: из них с доступом к ресурсам Интернета | O29: 9
A30: Мультимедийные проекторы | O30: 10
A31: Интерактивные доски | O31: 11
A32: Принтеры | O32: 12
... A34: Многофункциональные устройства (МФУ, выполняющие операции печати, сканирования, копирования) | O34: 14

Sheet Раздел 6.1
A14: Раздел 6. Финансово-экономическая деятельность организации
A15: 6.1.Распределение объема средств организации по источникам их получения и видам деятельности
A16: Код по ОКЕИ: тысяча рублей – 384 (с одним десятичным знаком)
A17: Наименование показателей | O17: № строки | P17: Всего (сумма гр. 4, 7) | Q17: в том числе по видам деятельности
Q18: образова-тельная | R18: из нее (из гр. 4): | T18: прочие виды
R19: по программам профес-сионального обучения | S19: по дополни-тельным профес-сиональным программам
A20: 1 | O20: 2 | P20: 3 | Q20: 4 | R20: 5 | S20: 6 | T20: 7
A21: Объем поступивших средств (за отчетный год) – всего (сумма строк 02, 06, 07, 08, 09) | O21: 1
A22: в том числе средства: бюджетов всех уровней (субсидий) – всего (сумма строк 03–05) | O22: 2
A23: в том числе бюджета: федерального | O23: 3
A24: субъекта Российской Федерации | O24: 4
A25: местного | O25: 5
A26: организаций | O26: 6
A27: населения | O27: 7
A28: внебюджетных фондов | O28: 8
A29: иностранных источников | O29: 9
A30: Справка 7. Остаток средств: на начало отчетного года (тысяча рублей) | O30: 10
A31: на конец отчетного года (тысяча рублей) | O31: 11

Sheet Раздел 6.2
A15: 6.2. Расходы организации
A16: (за отчетный год)
A17: Код по ОКЕИ: тысяча рублей – 384 (с одним десятичным знаком)
A18: Наименование показателей | O18: № строки | P18: Всего | Q18: в том числе осуществляемые
Q19: за счет средств бюджетов всех уровней (субсидий) | R19: из них (из гр. 4) - за счет средств на выполнение государственного (муниципального) задания (7)
A20: 1 | O20: 2 | P20: 3 | Q20: 4 | R20: 5
A21: Расходы (сумма строк 02, 06, 13, 14) | O21: 1
A22: в том числе: оплата труда и начисления на выплаты по оплате труда (сумма строк 03–05) | O22: 2
A23: заработная плата | O23: 3
A24: прочие выплаты | O24: 4
A25: начисления на выплаты по оплате труда | O25: 5
A26: оплата работ, услуг (сумма строк 07–12) | O26: 6
A27: услуги связи | O27: 7
A28: транспортные услуги | O28: 8
A29: коммунальные услуги | O29: 9
A30: арендная плата за пользование имуществом | O30: 10
A31: работы, услуги по содержанию имущества | O31: 11
A32: прочие работы, услуги | O32: 12
... A41: Справка 9. Расходы, связанные с содержанием общежитий (из строки 01 графы 3) (тысяча рублей) | O41: 21
A43: 7 -Укажите по графе 5 строке 01 знак 0, если организация не получает средства на выполнение государственного (муниципального) задания.

Sheet Раздел 6.3
A15: 6.3. Сведения о численности и оплате труда работников организации
A16: Коды по ОКЕИ: человек – 792; человек – 792(с одним десятичным знаком); тысяча рублей – 384 (с одним десятичным знаком)
A17: Наименование показателей | O17: № строки | P17: Средняя численность работников, человек | R17: Фонд начисленной заработной платы работников, тыс руб | U17: Фонд начисленной заработной платы работников по источникам финансирования, тыс руб
P18: списочного состава (без внешних совмести-телей) (8) | Q18: внешних совмести- телей (9) | R18: списочного состава (без внешних совместителей) | T18: внешних совместителей (сумма граф 11, 12 и 13) | U18: из гр.5 списочного состава (без внешних совместителей) | X18: из гр.7 внешних совместителей
R19: всего (сумма граф 8, 9, 10) | S19: в том числе по внутреннему совмести-тельству (10) | U19: за счет средств бюджетов всех уровней (субсидий) | V19: ОМС (11) | W19: за счет средств от приносящей доход деятельности | X19: за счет средств бюджетов всех уровней (субсидий) | Y19: ОМС | Z19: за счет средств от приносящей доход деятельности
A20: 1 | O20: 2 | P20: 3 | Q20: 4 | R20: 5 | S20: 6 | T20: 7 | U20: 8 | V20: 9 | W20: 10 | X20: 11 | Y20: 12 | Z20: 13
A21: Всего работников (сумма строк 02, 03, 06, 07) | O21: 1
A22: в том числе: руководящие работники | O22: 2
A23: педагогические работники | O23: 3
A24: из них: преподаватели | O24: 4
A25: мастера производственного обучения | O25: 5
A26: учебно-вспомогательный персонал | O26: 6
A27: иной персонал | O27: 7
A28: Справка 10. Численность человек одновременной подготовки (обучения) (чел) | O28: 8
A29: Численность человек одновременной подготовки, приведенное к очной форме обучения (с одним десятичным знаком) (12) | O29: 9
A30: Среднегодовая численность слушателей (сумма строк 11, 12) (с одним десятичным знаком) | O30: 10
A31: в том числе по программам: профессионального обучения (чел) | O31: 11
A32: дополнительным профессиональным программам (чел) | O32: 12
A34: 8 - Среднесписочная численность работников.
A35: 9 - Исчисляется пропорционально фактически отработанному времени.
A36: 10 - Включая вознаграждение за работу по договорам гражданско-правового характера, заключенным работником списочного состава со своей организацией.
A37: 11 - Обязательное медицинское страхование
A38: 12 - Из расчета соответственно 1.0; 0.25; 0.1 для очной, очно-заочной и заочной форм обучения.

Sheet Раздел 6.4
A17: 6.4. Затраты на внедрение и использование цифровых технологий в отчетном году
A18: Код по ОКЕИ: тысяча рублей – 384 (с одним десятичным знаком)
A19: Наименование показателей | O19: № строки | P19: Всего
A20: 1 | O20: 2 | P20: 3
A21: Затраты на внедрение и использование цифровых технологий – всего (сумма строк 03, 12) | O21: 1
A22: из них: затраты на продукты и услуги в области информационной безопасности | O22: 2
A23: из строки 01: Внутренние затраты на внедрение и использование цифровых технологий | O23: 3
A24: из них: на приобретение машин и оборудования, связанных с цифровыми технологиями, а также техническое обслуживание, модернизацию, текущий и капитальный ремонт, выполненные собственными силами | O24: 4
A25: из них на приобретение: вычислительной техники и оргтехники | O25: 5
A26: коммуникационного оборудования | O26: 6
A27: на приобретение программного обеспечения, адаптацию и доработку программного обеспечения, выполненные собственными силами | O27: 7
A28: в том числе российского программного обеспечения | O28: 8
A29: на оплату услуг электросвязи | O29: 9
A30: в том числе на оплату доступа к Интернету | O30: 10
A31: на приобретение цифрового контента (книги, музыкальные произведения, изображения, видео в электронном виде; цифровые модели и схемы (программы) обработки деталей) | O31: 11
A32: Внешние затраты на внедрение и использование цифровых технологий | O32: 12

Sheet Раздел 6.5
A17: 6.5. Источники финансирования внутренних затрат на внедрение и использование цифровых технологий
A18: Код по ОКЕИ: тысяча рублей – 384 (с одним десятичным знаком)
A19: Наименование показателей | O19: № строки | P19: Всего
A20: 1 | O20: 2 | P20: 3
A21: Внутренние затраты на внедрение и использование цифровых технологий (сумма строк 02, 03, 04) | O21: 1
A22: в том числе по источникам финансирования: собственные средства организации | O22: 2
A23: средства бюджетов всех уровней | O23: 3
A24: прочие привлеченные средства | O24: 4
A25: из них: некоммерческих организаций | O25: 5
A26: физических лиц | O26: 6
A29: Должностное лицо, ответственное за предоставление первичных статистических данных (лицо, уполномоченное предоставлять первичные статистические данные от имени юридического лица) или от имени гражданина, осуществляющего предпринимательскую
A30: деятельность без образования юридического лица
O31: (должность) | S31: (Ф.И.О.) | W31: (подпись)
O34: (номер контактного телефона) | S34: (E-mail) | W34: (дата составления документа)

Sheet Флак

Sheet Spravochnik
A2: 0000 | B2: 0 | C2: Hет | D2: 0
A3: 0001 | B3: 10003 | C3: Авербандщик | D3: 794
A4: 0002 | B4: 881794 | C4: Авиационный механик по криогенным системам | D4: 1
A5: 0003 | B5: 10005 | C5: Авиационный механик по планеру и двигателям | D5: 2
A6: 0004 | B6: 10007 | C6: Авиационный механик по приборам и электрооборудованию | D6: 3
A7: 0005 | B7: 10008 | C7: Авиационный механик по радиооборудованию | D7: 4
A8: 0006 | B8: 10013 | C8: Автоклавщик (по типам производств) | D8: 3190
A9: 0007 | B9: 10014 | C9: Автоклавщик (по типам производств) | D9: 3190
A10: 0008 | B10: 10015 | C10: Автоклавщик (по типам производств) | D10: 3190
A11: 0009 | B11: 10016 | C11: Автоклавщик литья под давлением | D11: 2103
A12: 0010 | B12: 10017 | C12: Автоклавщик на запарке брикетов | D12: 396
A13: 0011 | B13: 10019 | C13: Автоклавщик-сушильщик аккумуляторных пластин в производстве свинцовых аккумуляторов | D13: 2580
... A5143: 5141 | B5143: 19975 | C5143: Юстировщик оптических приборов | D5143: 2934
